README
setup.py
touch4pi.py
touch4pi.egg-info/PKG-INFO
touch4pi.egg-info/SOURCES.txt
touch4pi.egg-info/dependency_links.txt
touch4pi.egg-info/requires.txt
touch4pi.egg-info/top_level.txt