Metadata-Version: 1.0
Name: touch4pi
Version: 0.1.1
Summary: Python library for interfacing with the Touch4Pi board
Home-page: https://github.com/CyntechUK/touch4pi
Author: Jason Barnett
Author-email: jason.barnett@cyntech.co.uk
License: MIT
Platform: UNKNOWN
